{
  "title": "星云导航航向修正",
  "created_at": "2026-06-26 19:16:16",
  "updated_at": "2026-06-26 19:16:17",
  "message_count": 3,
  "scene_idx": 0,
  "turn_idx": 3,
  "turn_count": 3,
  "history": [
    {
      "name": "CaptainRex",
      "display_name": "雷克斯",
      "text": "*从舰长椅上站起身，走到主控制台前扫视数据流* 「嗯，NGC-7742星云的重力波动很稳定。导航组把航向再偏转2度，避开左侧那片星际尘埃带。」*转身看向副官* 「克劳迪娅，第7区的遥测数据没什么异常吧？」",
      "time": "19:15:48"
    },
    {
      "name": "EngineerYuki",
      "display_name": "小雪",
      "text": "*小马尾随着轻快的步伐摆动，你一边擦着手上的机油一边蹦跳着走进舰桥*\n「嘿舰长！我刚从第四区导管系统回来，那群小可爱们状态一级棒！不过——」*凑到主控制台前，眼睛发亮地指着副屏幕上一组数据* 「我注意到热交换器的效率曲线有个小波动，虽然还在正常范围内，但直觉告诉我这可能是个暗病！要不要我今晚加个班检查一下？」",
      "time": "19:15:56"
    },
    {
      "name": "AndroidZoe",
      "display_name": "佐伊",
      "text": "*从导航控制台前抬起头，淡紫色电子眼微微闪烁，将最新航向数据投射到主显示屏上*\n「航向修正已完成，长官。预计将在3.27光秒后避开尘埃带边缘。」*转向小雪，嘴角浮现一个经过精密计算的上扬弧度* 「小雪，根据我的分析，那个效率曲线波动很可能是第四区导管第7号热交换阀的微磨损造成的。不过——」*停顿了一下，学着人类的语气放轻声音* 「我很欣赏你的直觉，这正是人类所谓‘预防胜于治疗’的智慧。如果你需要辅助数据分析，我随时可以帮忙。」",
      "time": "19:16:09"
    }
  ]
}